{
    "domain": "hentai-paradise.com",
    "owner": {},
    "source": [
        "DuckDuckGo-FR"
    ],
    "prevalence": 0.000101,
    "sites": 1,
    "subdomains": [],
    "cnames": [],
    "fingerprinting": 0,
    "resources": [
        {
            "rule": "hentai-paradise\\.com\\/wp-content\\/plugins\\/gtranslate\\/flags\\/16\\/en-us\\.png",
            "cookies": 0,
            "fingerprinting": 0,
            "subdomains": [],
            "apis": {},
            "sites": 2,
            "prevalence": 0.000201,
            "cnames": [],
            "responseHashes": [
                "e3b0c44298fc1c149afbf4c8996fb92427ae41e4649b934ca495991b7852b855"
            ],
            "type": "Image",
            "firstPartyCookies": {},
            "firstPartyCookiesSent": {},
            "exampleSites": [
                "hentai-paradise.net",
                "www.hentai-paradise.net"
            ]
        },
        {
            "rule": "hentai-paradise\\.com\\/wp-content\\/plugins\\/gtranslate\\/flags\\/16\\/fr\\.png",
            "cookies": 0,
            "fingerprinting": 0,
            "subdomains": [],
            "apis": {},
            "sites": 2,
            "prevalence": 0.000201,
            "cnames": [],
            "responseHashes": [
                "e3b0c44298fc1c149afbf4c8996fb92427ae41e4649b934ca495991b7852b855"
            ],
            "type": "Image",
            "firstPartyCookies": {},
            "firstPartyCookiesSent": {},
            "exampleSites": [
                "hentai-paradise.net",
                "www.hentai-paradise.net"
            ]
        },
        {
            "rule": "hentai-paradise\\.com\\/wp-content\\/plugins\\/gtranslate\\/flags\\/16\\/ja\\.png",
            "cookies": 0,
            "fingerprinting": 0,
            "subdomains": [],
            "apis": {},
            "sites": 2,
            "prevalence": 0.000201,
            "cnames": [],
            "responseHashes": [
                "e3b0c44298fc1c149afbf4c8996fb92427ae41e4649b934ca495991b7852b855"
            ],
            "type": "Image",
            "firstPartyCookies": {},
            "firstPartyCookiesSent": {},
            "exampleSites": [
                "hentai-paradise.net",
                "www.hentai-paradise.net"
            ]
        }
    ],
    "categories": [],
    "performance": {},
    "cookies": 0,
    "types": {
        "Image": 6
    },
    "nameservers": [
        "nick.ns.cloudflare.com",
        "wanda.ns.cloudflare.com"
    ]
}