{
    "domain": "smilewanted.com",
    "owner": {},
    "source": [
        "DuckDuckGo-CH"
    ],
    "prevalence": 0.00642,
    "sites": 64,
    "subdomains": [
        "prebid",
        "csync",
        "static",
        "tags-videos"
    ],
    "cnames": [],
    "fingerprinting": 1,
    "resources": [
        {
            "rule": "smilewanted\\.com\\/",
            "cookies": 0,
            "fingerprinting": 0,
            "subdomains": [
                "prebid"
            ],
            "apis": {},
            "sites": 48,
            "prevalence": 0.00482,
            "cnames": [],
            "responseHashes": [
                "e3b0c44298fc1c149afbf4c8996fb92427ae41e4649b934ca495991b7852b855"
            ],
            "type": "XHR",
            "firstPartyCookies": {},
            "firstPartyCookiesSent": {},
            "exampleSites": [
                "en.bab.la",
                "onepiecechapters.com",
                "www.neueroeffnung.info",
                "www.supersoluce.com",
                "lexikon.stangl.eu",
                "lebensweisheiten-sprueche.ch",
                "onepiece-tube.com",
                "www.applosungen.com",
                "vitux.com",
                "plantuml.com",
                "reseauinternational.net",
                "answerstoall.com",
                "www.botasot.info",
                "jailbreak-mag.de",
                "www.howtoforge.com",
                "www.sofoot.com",
                "www.pravda-tv.com",
                "www.collinsdictionary.com",
                "angelnumber.org",
                "buzzmonclick.net"
            ]
        },
        {
            "rule": "smilewanted\\.com\\/",
            "cookies": 0,
            "fingerprinting": 0,
            "subdomains": [
                "csync"
            ],
            "apis": {},
            "sites": 43,
            "prevalence": 0.00432,
            "cnames": [],
            "responseHashes": [
                "e61b3c8130d4175be823e3ffd547d878bec17f1a76d75ab67adac8865ab6465d"
            ],
            "type": "Document",
            "firstPartyCookies": {},
            "firstPartyCookiesSent": {},
            "exampleSites": [
                "en.bab.la",
                "www.generacodice.com",
                "reseauinternational.net",
                "www.opex360.com",
                "zeperfs.com",
                "plantuml.com",
                "www.was-war-wann.de",
                "www.hisse-et-oh.com",
                "les-raccourcis-clavier.fr",
                "vitux.com",
                "www.iphonehacks.com",
                "de.bab.la",
                "www.parkerlebnis.de",
                "chefsimon.com",
                "www.heimhelden.de",
                "instazoomer.de",
                "answerstoall.com",
                "www.pravda-tv.com",
                "www.botasot.info",
                "angelnumber.org"
            ]
        },
        {
            "rule": "smilewanted\\.com\\/js\\/decode_consent\\/decode_consent\\.js",
            "cookies": 0,
            "fingerprinting": 0,
            "subdomains": [
                "static"
            ],
            "apis": {},
            "sites": 56,
            "prevalence": 0.00562,
            "cnames": [],
            "responseHashes": [
                "eb4db95cf7c97ce22bd98d1b95dfd82204843cc8854cbe0b3b6b93be4fa41a2f"
            ],
            "type": "Script",
            "firstPartyCookies": {},
            "firstPartyCookiesSent": {},
            "exampleSites": [
                "en.bab.la",
                "lexikon.stangl.eu",
                "www.collinsdictionary.com",
                "plantuml.com",
                "www.millenium.org",
                "moto-inserate.ch",
                "expressantworten.com",
                "smartandroid.fr",
                "www.howtoforge.com",
                "www.it-connect.fr",
                "onepiece-tube.com",
                "buzzmonclick.net",
                "www.toutelatele.com",
                "www.senscritique.com",
                "www.haaretz.com",
                "www.melty.fr",
                "www.hisse-et-oh.com",
                "www.autoplus.fr",
                "angelnumber.org",
                "www.iphonehacks.com"
            ]
        },
        {
            "rule": "smilewanted\\.com\\/drop_cookie_sw\\.php",
            "cookies": 0.00381,
            "fingerprinting": 0,
            "subdomains": [
                "csync"
            ],
            "apis": {},
            "sites": 39,
            "prevalence": 0.00391,
            "cnames": [],
            "responseHashes": [
                "e3b0c44298fc1c149afbf4c8996fb92427ae41e4649b934ca495991b7852b855"
            ],
            "type": "Document",
            "firstPartyCookies": {},
            "firstPartyCookiesSent": {},
            "exampleSites": [
                "en.bab.la",
                "www.applosungen.com",
                "vitux.com",
                "instazoomer.de",
                "zeperfs.com",
                "infos-geek.com",
                "www.delftstack.com",
                "www.pravda-tv.com",
                "smartandroid.fr",
                "planetes360.fr",
                "answerstoall.com",
                "chefsimon.com",
                "www.ecranlarge.com",
                "angelnumber.org",
                "www.howtoforge.com",
                "www.generacodice.com",
                "reseauinternational.net",
                "www.it-connect.fr",
                "www.collinsdictionary.com",
                "moto-inserate.ch"
            ]
        },
        {
            "rule": "smilewanted\\.com\\/set_partner_userid_get\\/outbrain\\/",
            "cookies": 0,
            "fingerprinting": 0,
            "subdomains": [
                "csync"
            ],
            "apis": {},
            "sites": 35,
            "prevalence": 0.00351,
            "cnames": [],
            "responseHashes": [
                "e3b0c44298fc1c149afbf4c8996fb92427ae41e4649b934ca495991b7852b855"
            ],
            "type": "Document",
            "firstPartyCookies": {},
            "firstPartyCookiesSent": {},
            "exampleSites": [
                "en.bab.la",
                "www.haaretz.com",
                "expressantworten.com",
                "www.opex360.com",
                "www.mvorganizing.org",
                "www.pblvreplay.com",
                "buzzmonclick.net",
                "www.delftstack.com",
                "infos-geek.com",
                "reseauinternational.net",
                "instazoomer.de",
                "www.generacodice.com",
                "smartandroid.fr",
                "www.it-connect.fr",
                "chefsimon.com",
                "moto-inserate.ch",
                "www.pravda-tv.com",
                "www.supersoluce.com",
                "zeperfs.com",
                "answerstoall.com"
            ]
        },
        {
            "rule": "smilewanted\\.com\\/jwplayer-8\\.11\\.7\\/jwplayer\\.js",
            "cookies": 0,
            "fingerprinting": 2,
            "subdomains": [
                "static"
            ],
            "apis": {
                "Navigator.prototype.userAgent": 5,
                "Navigator.prototype.platform": 5,
                "PerformanceTiming.prototype.navigationStart": 5,
                "window.localStorage": 5,
                "HTMLMediaElement.prototype.canPlayType": 5,
                "CanvasRenderingContext2D.prototype.getImageData": 5
            },
            "sites": 5,
            "prevalence": 0.000502,
            "cnames": [],
            "responseHashes": [
                "2c81e9a9aa0d70479be86c7b8aa5a01cbc1f642c1c914d6e7bc101b8ef9be7c0"
            ],
            "type": "Script",
            "firstPartyCookies": {},
            "firstPartyCookiesSent": {},
            "exampleSites": [
                "icalendrier.fr",
                "mcetv.fr",
                "moto-station.com",
                "planetes360.fr",
                "www.toutelatele.com"
            ]
        },
        {
            "rule": "smilewanted\\.com\\/track\\/analytics\\/adcall\\.php",
            "cookies": 0,
            "fingerprinting": 0,
            "subdomains": [
                "prebid"
            ],
            "apis": {},
            "sites": 6,
            "prevalence": 0.000602,
            "cnames": [],
            "responseHashes": [
                "e3b0c44298fc1c149afbf4c8996fb92427ae41e4649b934ca495991b7852b855"
            ],
            "type": "XHR",
            "firstPartyCookies": {},
            "firstPartyCookiesSent": {},
            "exampleSites": [
                "icalendrier.fr",
                "mcetv.fr",
                "moto-station.com",
                "planetes360.fr",
                "www.francesoir.fr",
                "www.toutelatele.com"
            ]
        },
        {
            "rule": "smilewanted\\.com\\/config_infeed\\.php",
            "cookies": 0,
            "fingerprinting": 0,
            "subdomains": [
                "tags-videos"
            ],
            "apis": {},
            "sites": 3,
            "prevalence": 0.000301,
            "cnames": [],
            "responseHashes": [
                "c4cd57bb9eb603b929ac231fb491732b6abddbe36e336dd2b4f865df8d3fc5f8",
                "7ac91d534e4adf614f940341b2930677a7ae0f5a208c95cd3976cc9fbaf72638"
            ],
            "type": "Script",
            "firstPartyCookies": {},
            "firstPartyCookiesSent": {},
            "exampleSites": [
                "icalendrier.fr",
                "www.francesoir.fr",
                "www.toutelatele.com"
            ]
        },
        {
            "rule": "smilewanted\\.com\\/img\\/native_link\\.svg",
            "cookies": 0,
            "fingerprinting": 0,
            "subdomains": [
                "static"
            ],
            "apis": {},
            "sites": 3,
            "prevalence": 0.000301,
            "cnames": [],
            "responseHashes": [
                "09fba596f1ba572cf4b3ceb9c1f3962d1b75bbb4a6d6d7707f1f93e2fe889aee"
            ],
            "type": "Image",
            "firstPartyCookies": {},
            "firstPartyCookiesSent": {},
            "exampleSites": [
                "icalendrier.fr",
                "www.francesoir.fr",
                "www.toutelatele.com"
            ]
        },
        {
            "rule": "smilewanted\\.com\\/infos_corner_video\\.php",
            "cookies": 0,
            "fingerprinting": 0,
            "subdomains": [
                "tags-videos"
            ],
            "apis": {},
            "sites": 5,
            "prevalence": 0.000502,
            "cnames": [],
            "responseHashes": [
                "399ab8e6119208a3fc567786bdb48d11c0896b168786752c62481a747947a9b9",
                "8f4472079944dcb059ef8fc5a77c78f1d1e470e4aa53c6b081acb7335c69a4c2",
                "6338174a19bf3dfa29303a2ee180b0d6e89edf2f0beb9c17a37bc79602e6b077",
                "e25f45dd8a88a18eaa49dfbb5604c623a8d03e1a7ddd1f21571a1cf1c26ce28f"
            ],
            "type": "Script",
            "firstPartyCookies": {},
            "firstPartyCookiesSent": {},
            "exampleSites": [
                "icalendrier.fr",
                "mcetv.fr",
                "moto-station.com",
                "planetes360.fr",
                "www.toutelatele.com"
            ]
        },
        {
            "rule": "smilewanted\\.com\\/js\\/prebid\\/prebid_corner\\.js",
            "cookies": 0,
            "fingerprinting": 1,
            "subdomains": [
                "static"
            ],
            "apis": {
                "Navigator.prototype.userAgent": 5,
                "Navigator.prototype.cookieEnabled": 5,
                "window.sessionStorage": 5
            },
            "sites": 5,
            "prevalence": 0.000502,
            "cnames": [],
            "responseHashes": [
                "e0fa8a0d41d24e12ba6fbbf93f5bbd4e77d719ae43156857af9b908297bb6a10"
            ],
            "type": "Script",
            "firstPartyCookies": {},
            "firstPartyCookiesSent": {},
            "exampleSites": [
                "icalendrier.fr",
                "mcetv.fr",
                "moto-station.com",
                "planetes360.fr",
                "www.toutelatele.com"
            ]
        },
        {
            "rule": "smilewanted\\.com\\/",
            "cookies": 0,
            "fingerprinting": 0,
            "subdomains": [
                "csync"
            ],
            "apis": {},
            "sites": 16,
            "prevalence": 0.00161,
            "cnames": [],
            "responseHashes": [
                "62c9640b0cb951e587fe9b4780d148db797812b4e693e4d1a4e0af75f4f97035"
            ],
            "type": "Script",
            "firstPartyCookies": {},
            "firstPartyCookiesSent": {},
            "exampleSites": [
                "mcetv.fr",
                "planetes360.fr",
                "www.auto-moto.com",
                "www.autoplus.fr",
                "www.bibamagazine.fr",
                "www.ecranlarge.com",
                "www.francesoir.fr",
                "www.haaretz.com",
                "www.maison-travaux.fr",
                "www.mariefrance.fr",
                "www.melty.fr",
                "www.millenium.org",
                "www.sofoot.com",
                "www.supersoluce.com",
                "www.topsante.com",
                "www.toutelatele.com"
            ]
        }
    ],
    "categories": [],
    "performance": {},
    "cookies": 0.00381,
    "types": {
        "XHR": 54,
        "Document": 117,
        "Script": 90,
        "Image": 3
    },
    "nameservers": [
        "nina.ns.cloudflare.com",
        "peyton.ns.cloudflare.com"
    ]
}