{
    "domain": "3gateway.net",
    "owner": {},
    "source": [
        "DuckDuckGo-US"
    ],
    "prevalence": 0.0000152,
    "sites": 2,
    "subdomains": [
        "ydn243"
    ],
    "cnames": [],
    "fingerprinting": 2,
    "resources": [
        {
            "rule": "3gateway\\.net\\/bf\\/7769d5cf-5b9b-4a61-a4b5-3ea28784f993",
            "cookies": 0,
            "fingerprinting": 0,
            "subdomains": [
                "ydn243"
            ],
            "apis": {},
            "sites": 2,
            "prevalence": 0.0000152,
            "cnames": [],
            "responseHashes": [
                "be025586773fa00c78a905690325f884103032d5c211c30d34da2dfdfbdf054f"
            ],
            "type": "XHR",
            "firstPartyCookies": {},
            "firstPartyCookiesSent": {},
            "exampleSites": [
                "three.co.uk",
                "new.three.co.uk"
            ]
        }
    ],
    "categories": [],
    "performance": {},
    "cookies": 0.00000759,
    "types": {
        "XHR": 2
    },
    "nameservers": [
        "ns1-05.azure-dns.com",
        "ns2-05.azure-dns.net",
        "ns3-05.azure-dns.org",
        "ns4-05.azure-dns.info"
    ]
}