{
    "domain": "geoip-db.com",
    "owner": {},
    "source": [
        "DuckDuckGo-US"
    ],
    "prevalence": 0.000428,
    "sites": 62,
    "subdomains": [],
    "cnames": [],
    "fingerprinting": 0,
    "resources": [
        {
            "rule": "geoip-db\\.com\\/jsonp\\/",
            "cookies": 0,
            "fingerprinting": 0,
            "subdomains": [],
            "apis": {},
            "sites": 25,
            "prevalence": 0.000173,
            "cnames": [],
            "responseHashes": [
                "ea0268a4e4be2a5a560a3ce0d724eb1ae1c7f680bdf3f2fb69db72685983d3c0"
            ],
            "type": "Script",
            "firstPartyCookies": {},
            "firstPartyCookiesSent": {},
            "exampleSites": [
                "www.songandpraise.org",
                "biography.yourdictionary.com",
                "www.savings.com.au",
                "quotes.yourdictionary.com",
                "aviewfrommyseat.com",
                "grammar.yourdictionary.com",
                "toptenzbest.com",
                "www.catholic-saints.info",
                "www.freshpair.com",
                "www.skidsteersolutions.com",
                "education.yourdictionary.com",
                "www.metalsupermarkets.com",
                "smarthomepursuits.com",
                "www.computrabajo.com.mx",
                "abbreviations.yourdictionary.com",
                "examples.yourdictionary.com",
                "www.plowhearth.com",
                "www.zeromotorcycles.com",
                "reference.yourdictionary.com",
                "www.pestwiki.com"
            ]
        },
        {
            "rule": "geoip-db\\.com\\/jsonp",
            "cookies": 0,
            "fingerprinting": 0,
            "subdomains": [],
            "apis": {},
            "sites": 20,
            "prevalence": 0.000138,
            "cnames": [],
            "responseHashes": [
                "ea0268a4e4be2a5a560a3ce0d724eb1ae1c7f680bdf3f2fb69db72685983d3c0"
            ],
            "type": "Script",
            "firstPartyCookies": {},
            "firstPartyCookiesSent": {},
            "exampleSites": [
                "yourdictionary.com",
                "aviewfrommyseat.com",
                "biography.yourdictionary.com",
                "education.yourdictionary.com",
                "examples.yourdictionary.com",
                "grammar.yourdictionary.com",
                "nootriment.com",
                "quotes.yourdictionary.com",
                "reference.yourdictionary.com",
                "spanish.yourdictionary.com",
                "www.catholic-saints.info",
                "www.chickadvisor.com",
                "www.computrabajo.com.mx",
                "www.freshpair.com",
                "www.metalsupermarkets.com",
                "www.plowhearth.com",
                "www.savings.com.au",
                "www.skidsteersolutions.com",
                "www.songandpraise.org",
                "www.zeromotorcycles.com"
            ]
        },
        {
            "rule": "geoip-db\\.com\\/json\\/geoip\\.php",
            "cookies": 0,
            "fingerprinting": 0,
            "subdomains": [],
            "apis": {},
            "sites": 3,
            "prevalence": 0.0000207,
            "cnames": [],
            "responseHashes": [
                "ea0268a4e4be2a5a560a3ce0d724eb1ae1c7f680bdf3f2fb69db72685983d3c0",
                "777271a0c78cf5126b331afd9d0f0f7ccac00d4f2632c197cb007b98f6b69d20"
            ],
            "type": "Script",
            "firstPartyCookies": {},
            "firstPartyCookiesSent": {},
            "exampleSites": [
                "friendseat.com",
                "www.hiltonheadisland.org",
                "www.medicalmarijuanadispensaries.co"
            ]
        },
        {
            "rule": "geoip-db\\.com\\/json\\/",
            "cookies": 0,
            "fingerprinting": 0,
            "subdomains": [],
            "apis": {},
            "sites": 8,
            "prevalence": 0.0000552,
            "cnames": [],
            "responseHashes": [
                "6bb79bebe06060023cb0127d342820102faf760887e29bb2c0530a7944067cc4"
            ],
            "type": "XHR",
            "firstPartyCookies": {},
            "firstPartyCookiesSent": {},
            "exampleSites": [
                "asianetnews.com",
                "puppyspot.com",
                "slicelife.com",
                "www.battlbox.com",
                "www.dogtopia.com",
                "www.khaleejtimes.com",
                "www.payoneer.com",
                "www.solitr.com"
            ]
        },
        {
            "rule": "geoip-db\\.com\\/json\\/cde44b00-5d23-11e9-9c3a-9df5494d7a9f",
            "cookies": 0,
            "fingerprinting": 0,
            "subdomains": [],
            "apis": {},
            "sites": 2,
            "prevalence": 0.0000138,
            "cnames": [],
            "responseHashes": [
                "6bb79bebe06060023cb0127d342820102faf760887e29bb2c0530a7944067cc4"
            ],
            "type": "XHR",
            "firstPartyCookies": {},
            "firstPartyCookiesSent": {},
            "exampleSites": [
                "edelmetall-handel.de",
                "www.edelmetall-handel.de"
            ]
        },
        {
            "rule": "geoip-db\\.com\\/jsonp\\/58112090-850c-11e9-9737-fdaf87ce918a",
            "cookies": 0,
            "fingerprinting": 0,
            "subdomains": [],
            "apis": {},
            "sites": 2,
            "prevalence": 0.0000138,
            "cnames": [],
            "responseHashes": [
                "ea0268a4e4be2a5a560a3ce0d724eb1ae1c7f680bdf3f2fb69db72685983d3c0"
            ],
            "type": "Script",
            "firstPartyCookies": {},
            "firstPartyCookiesSent": {},
            "exampleSites": [
                "motionrc.com",
                "www.motionrc.com"
            ]
        }
    ],
    "categories": [],
    "performance": {},
    "cookies": 0,
    "types": {
        "Script": 50,
        "XHR": 10
    },
    "nameservers": [
        "ns1.digitalocean.com",
        "ns2.digitalocean.com",
        "ns3.digitalocean.com"
    ]
}